Clumsy/__init__.py
Clumsy/__version__.py
Clumsy/io/EdfWriting.py
Clumsy/io/GetData.py
Clumsy/io/__init__.py
Clumsy/io/loadmat.py
Clumsy/io/loadmicros.py
Clumsy/io/pickleio.py
Clumsy/misc/BigDataAssignment1.py
Clumsy/misc/__init__.py
Clumsy/misc/inherit_docstrings.py
Clumsy/misc/matplotlibmisc.py
Clumsy/misc/misc.py
Clumsy/misc/polarplots.py
Clumsy/signal/__init__.py
Clumsy/signal/butterworth.py
Clumsy/signal/circlestats.py
Clumsy/signal/datachop.py
Clumsy/signal/fft.py
Clumsy/signal/guassiansmoothing.py
Clumsy/signal/hilbert.py
Clumsy/signal/notchfilter.py
Clumsy/signal/rolling.py
Clumsy/signal/rootmeansquare.py
Clumsy/signal/timeseriesLF.py
Clumsy/sleep/__init__.py
Clumsy/sleep/base.py
Clumsy/sleep/data_organization.py
Clumsy/sleep/detect.py
Clumsy/sleep/detection_utils.py
Clumsy/sleep/slowwaves.py
Clumsy/sleep/staging.py
Clumsy/sleep/timeseries_brain_plot.py
Clumsy/sleep/transform_signal.py
Clumsy/sleep/visbrain_gui.py
Clumsy-0.0.5.dist-info/METADATA
Clumsy-0.0.5.dist-info/WHEEL
Clumsy-0.0.5.dist-info/top_level.txt
Clumsy-0.0.5.dist-info/RECORD
