Metadata-Version: 2.1
Name: Clumsy
Version: 0.0.5
Summary: A collection of scripts used in the Computational Memory Lab for timeseries analysis
Home-page: https://github.com/LoganJF/Clumsy
Author: Logan Fickling
Author-email: loganfickling@gmail.com
License: UNKNOWN
Platform: UNKNOWN
Requires-Python: >=3.6.0
Requires-Dist: pyedflib
Requires-Dist: mne
Requires-Dist: ptsa
Requires-Dist: scipy
Requires-Dist: numpy
Requires-Dist: xarray
Requires-Dist: pandas
Requires-Dist: six
Requires-Dist: cmlreaders
Requires-Dist: numba
Requires-Dist: visbrain
